{
  "description": "This techno song features programmed percussion. The kick is played on every count of the beat. A cymbal or shaker is played in sixteenth note patterns. This is accompanied by a synth playing a repetitive sequence. Another synth sound is played in bursts which has a warped sound effect. This song is an instrumental and has no voices. This song can be played in a club.",
  "general_mood": "",
  "genre_tags": [
    "techno"
  ],
  "lead_instrument": "synth",
  "accompaniment": "programmed percussion, synth",
  "tempo_and_rhythm": "sixteenth note patterns",
  "vocal_presence": "no voices",
  "production_quality": ""
}