{
  "description": "This music is an electric guitar instrumental. The tempo is medium with an amplified guitar lead harmony and synthesiser articulation. The music is not very clear as the recording quality is inferior, but the harmony is catchy, spirited and youthful.",
  "general_mood": "catchy, spirited, youthful",
  "genre_tags": [
    "electric guitar",
    "instrumental"
  ],
  "lead_instrument": "electric guitar",
  "accompaniment": "synthesiser",
  "tempo_and_rhythm": "medium",
  "vocal_presence": "none",
  "production_quality": "inferior"
}